{
  "unversionedId": "guides/required-directive",
  "id": "version-v13.0.0/guides/required-directive",
  "title": "@required Directive",
  "description": "Relay guide to @required",
  "source": "@site/versioned_docs/version-v13.0.0/guides/required-directive.md",
  "sourceDirName": "guides",
  "slug": "/guides/required-directive/",
  "permalink": "/docs/v13.0.0/guides/required-directive/",
  "draft": false,
  "editUrl": "https://github.com/rdkcentral/firebolt-documentation/versioned_docs/version-v13.0.0/guides/required-directive.md",
  "tags": [],
  "version": "v13.0.0",
  "lastUpdatedBy": "Author",
  "lastUpdatedAt": 1539502055,
  "formattedLastUpdatedAt": "10/14/2018",
  "frontMatter": {
    "id": "required-directive",
    "title": "@required Directive",
    "slug": "/guides/required-directive/",
    "description": "Relay guide to @required",
    "keywords": [
      "required",
      "directive",
      "optional",
      "nullthrows"
    ]
  }
}